reporter/__init__.py
reporter/cli.py
reporter/common.py
reporter/config.py
reporter/gh.py
reporter/grafeas.py
reporter/licence.py
reporter/sarif.py
reporter/utils.py
reporter/templates/base.html
reporter/templates/chart.html
reporter/templates/dep-all.html
reporter/templates/dep-report.html
reporter/templates/dep-summary.html
reporter/templates/header.html
reporter/templates/licence-all.html
reporter/templates/licence-chart.html
reporter/templates/licence-legend.html
reporter/templates/licence-report.html
reporter/templates/licence-summary.html
reporter/templates/sast-report.html
test/__init__.py
test/test_grafeas.py
test/test_licence.py
test/test_sarif.py
shiftleft_scan_reports-1.5.1.dist-info/METADATA
shiftleft_scan_reports-1.5.1.dist-info/WHEEL
shiftleft_scan_reports-1.5.1.dist-info/entry_points.txt
shiftleft_scan_reports-1.5.1.dist-info/top_level.txt
shiftleft_scan_reports-1.5.1.dist-info/RECORD
