Metadata-Version: 2.1
Name: shiftleft-scan-reports
Version: 1.5.1
Summary: Library for producing SARIF & html reports from ShiftLeft or AppThreat scan results
Home-page: https://github.com/ShiftLeftSecurity/scan-reports
Author: Team ShiftLeft
Author-email: hello@shiftleft.io
License: UNKNOWN
Platform: UNKNOWN
Classifier: Development Status :: 5 - Production/Stable
Classifier: Intended Audience :: Developers
Classifier: Intended Audience :: System Administrators
Classifier: Topic :: Utilities
Classifier: Topic :: Security
Classifier: Programming Language :: Python :: 3.6
Classifier: Programming Language :: Python :: 3.8
Classifier: Programming Language :: Python :: 3.9
Classifier: License :: OSI Approved :: MIT License
Classifier: Operating System :: OS Independent
Requires-Python: >=3.6
Requires-Dist: Jinja2
Requires-Dist: PyGitHub (==1.54.0.1)
Requires-Dist: joern2sarif
Requires-Dist: markdown
Requires-Dist: pyjwt
Requires-Dist: requests
Requires-Dist: rich
